setup.py
django_states/__init__.py
django_states/compat.py
django_states/conf.py
django_states/exceptions.py
django_states/fields.py
django_states/log.py
django_states/machine.py
django_states/model_methods.py
django_states/models.py
django_states/signals.py
django_states/tests.py
django_states/urls.py
django_states/views.py
django_states.egg-info/PKG-INFO
django_states.egg-info/SOURCES.txt
django_states.egg-info/dependency_links.txt
django_states.egg-info/top_level.txt
django_states/management/__init__.py
django_states/management/commands/__init__.py
django_states/management/commands/graph_states2.py
django_states/templatetags/__init__.py
django_states/templatetags/django_states.py
test_proj/__init__.py
test_proj/manage.py
test_proj/settings.py
test_proj/urls.py