Metadata-Version: 1.1
Name: django-states
Version: 1.6.5
Summary: State machine for django models
Home-page: https://github.com/citylive/django-states2
Author: Jonathan Slenders, Gert van Gool, Maarten Timmerman, Steven (rh0dium)
Author-email: jonathan.slenders@mobilevikings.com
License: BSD
Platform: UNKNOWN
Classifier: Intended Audience :: Developers
Classifier: Programming Language :: Python
Classifier: Operating System :: OS Independent
Classifier: Environment :: Web Environment
Classifier: Framework :: Django
